{
    "name": "SClumpAnimAssoc",
    "module": "",
    "scope": "",
    "kind": "class",
    "size": "0x2C",
    "alignment": 0,
    "comment": "",
    "members": [
        {
            "name": "m_pPrevClumpAnimAssoc",
            "type": "SClumpAnimAssoc *",
            "offset": 0,
            "size": 4
        },
        {
            "name": "m_pNextClumpAnimAssoc",
            "type": "SClumpAnimAssoc *",
            "offset": 4,
            "size": 4
        },
        {
            "name": "m_wNumBlendNodes",
            "type": "__int16",
            "offset": 8,
            "size": 2
        },
        {
            "name": "m_wAnimGroup",
            "type": "__int16",
            "offset": "0xA",
            "size": 2
        },
        {
            "name": "m_pAnimBlendNodeArray",
            "type": "CAnimBlendNode *",
            "offset": "0xC",
            "size": 4,
            "comment": "CAnimBlendNode *"
        },
        {
            "name": "m_pAnimBlendHierarchy",
            "type": "CAnimBlendHierarchy *",
            "offset": "0x10",
            "size": 4,
            "comment": "CAnimBlendHierarchy *"
        },
        {
            "name": "m_fBlendAmount",
            "type": "float",
            "offset": "0x14",
            "size": 4
        },
        {
            "name": "m_fBlendDelta",
            "type": "float",
            "offset": "0x18",
            "size": 4
        },
        {
            "name": "m_fCurrentTime",
            "type": "float",
            "offset": "0x1C",
            "size": 4
        },
        {
            "name": "fSpeed",
            "type": "float",
            "offset": "0x20",
            "size": 4
        },
        {
            "name": "fTimeStep",
            "type": "float",
            "offset": "0x24",
            "size": 4
        },
        {
            "name": "sAnimID",
            "type": "__int16",
            "offset": "0x28",
            "size": 2
        },
        {
            "name": "sFlags",
            "type": "__int16",
            "offset": "0x2A",
            "size": 2
        }
    ]
}