{
    "name": "CAEStreamThread",
    "module": "",
    "scope": "",
    "kind": "class",
    "size": "0x50",
    "alignment": 0,
    "comment": "",
    "members": [
        {
            "name": "hHandle",
            "type": "HANDLE",
            "offset": 0,
            "size": 4
        },
        {
            "name": "field_4",
            "type": "int",
            "offset": 4,
            "size": 4
        },
        {
            "name": "m_pStreamingChannel",
            "type": "_DWORD *",
            "offset": 8,
            "size": 4
        },
        {
            "name": "m_pMp3TrackLoader",
            "type": "int",
            "offset": "0xC",
            "size": 4
        },
        {
            "name": "m_bActive",
            "type": "char",
            "offset": "0x10",
            "size": 1
        },
        {
            "name": "field_11",
            "type": "char",
            "offset": "0x11",
            "size": 1
        },
        {
            "name": "field_12",
            "type": "_BYTE",
            "offset": "0x12",
            "size": 1
        },
        {
            "name": "field_13",
            "type": "_BYTE",
            "offset": "0x13",
            "size": 1
        },
        {
            "name": "field_14",
            "type": "_BYTE",
            "offset": "0x14",
            "size": 1
        },
        {
            "name": "field_15",
            "type": "char",
            "offset": "0x15",
            "size": 1
        },
        {
            "name": "m_bTrackStopped",
            "type": "char",
            "offset": "0x16",
            "size": 1
        },
        {
            "name": "field_17",
            "type": "char",
            "offset": "0x17",
            "size": 1
        },
        {
            "name": "field_18",
            "type": "int",
            "offset": "0x18",
            "size": 4
        },
        {
            "name": "field_1C",
            "type": "_DWORD",
            "offset": "0x1C",
            "size": 4
        },
        {
            "name": "field_20",
            "type": "_DWORD",
            "offset": "0x20",
            "size": 4
        },
        {
            "name": "field_24",
            "type": "_BYTE",
            "offset": "0x24",
            "size": 1
        },
        {
            "name": "field_25",
            "type": "char",
            "offset": "0x25",
            "size": 1
        },
        {
            "name": "field_26",
            "type": "char",
            "offset": "0x26",
            "size": 1
        },
        {
            "name": "field_27",
            "type": "char",
            "offset": "0x27",
            "size": 1
        },
        {
            "name": "field_28",
            "type": "int",
            "offset": "0x28",
            "size": 4
        },
        {
            "name": "m_nTrackLenghtMs",
            "type": "int",
            "offset": "0x2C",
            "size": 4
        },
        {
            "name": "m_nActiveTrackID",
            "type": "int",
            "offset": "0x30",
            "size": 4
        },
        {
            "name": "m_nPlayingTrackID",
            "type": "int",
            "offset": "0x34",
            "size": 4
        },
        {
            "name": "m_criticalSection",
            "type": "_RTL_CRITICAL_SECTION",
            "offset": "0x38",
            "size": "0x18"
        }
    ]
}