{
    "name": "CTransmissionGear",
    "module": "",
    "scope": "",
    "kind": "class",
    "size": "0xC",
    "alignment": 0,
    "comment": "",
    "members": [
        {
            "name": "m_fMaxVelocity",
            "type": "int",
            "offset": 0,
            "size": 4
        },
        {
            "name": "m_fChangeUpVelocity",
            "type": "float",
            "offset": 4,
            "size": 4
        },
        {
            "name": "m_fChangeDownVelocity",
            "type": "float",
            "offset": 8,
            "size": 4
        }
    ]
}