{
    "name": "RxPipelineModule",
    "module": "",
    "scope": "",
    "kind": "class",
    "size": "0x60",
    "alignment": 0,
    "comment": "",
    "members": [
        {
            "name": "rxPipesFreeList",
            "type": "int",
            "offset": 0,
            "size": 4
        },
        {
            "name": "vector",
            "type": "RxRenderStateVector",
            "offset": 4,
            "size": "0x2C"
        },
        {
            "name": "field_30",
            "type": "int",
            "offset": "0x30",
            "size": 4
        },
        {
            "name": "field_34",
            "type": "int",
            "offset": "0x34",
            "size": 4
        },
        {
            "name": "maxNodes",
            "type": "int",
            "offset": "0x38",
            "size": 4
        },
        {
            "name": "pPipeline",
            "type": "int",
            "offset": "0x3C",
            "size": 4
        },
        {
            "name": "field_40",
            "type": "int",
            "offset": "0x40",
            "size": 4
        },
        {
            "name": "field_44",
            "type": "int",
            "offset": "0x44",
            "size": 4
        },
        {
            "name": "field_48",
            "type": "int",
            "offset": "0x48",
            "size": 4
        },
        {
            "name": "field_4C",
            "type": "int",
            "offset": "0x4C",
            "size": 4
        },
        {
            "name": "field_50",
            "type": "int",
            "offset": "0x50",
            "size": 4
        },
        {
            "name": "field_54",
            "type": "int",
            "offset": "0x54",
            "size": 4
        },
        {
            "name": "field_58",
            "type": "int",
            "offset": "0x58",
            "size": 4
        },
        {
            "name": "field_5C",
            "type": "int",
            "offset": "0x5C",
            "size": 4
        }
    ]
}