{
    "name": "CImgDescriptor",
    "module": "",
    "scope": "",
    "kind": "class",
    "size": "0x30",
    "alignment": 0,
    "comment": "",
    "members": [
        {
            "name": "name",
            "type": "char[40]",
            "offset": 0,
            "size": "0x28"
        },
        {
            "name": "isNotPlayerImg",
            "type": "char",
            "offset": "0x28",
            "size": 1
        },
        {
            "name": "__align",
            "type": "char[3]",
            "offset": "0x29",
            "size": 3
        },
        {
            "name": "streamHandle",
            "type": "int",
            "offset": "0x2C",
            "size": 4
        }
    ]
}